storm_lists/P13.py
storm_lists/WG19.py
storm_lists/__init__.py
storm_lists/list.py
storm_lists-1.0.3.dist-info/METADATA
storm_lists-1.0.3.dist-info/WHEEL
storm_lists-1.0.3.dist-info/top_level.txt
storm_lists-1.0.3.dist-info/RECORD
