Metadata-Version: 2.4
Name: storm-lists
Version: 1.0.3
Summary: Implementations of geomagnetic storm list algorithms, including Walach & Grocott (2019).
Author-email: John C Coxon <work@johncoxon.co.uk>, Maria-Theresia Walach <m.walach@lancaster.ac.uk>
License-Expression: AGPL-3.0-or-later
Project-URL: doi, https://doi.org/10.5281/zenodo.17521944
Project-URL: repository, https://github.com/johncoxon/storm-lists
Keywords: geomagnetic storms
Classifier: Development Status :: 4 - Beta
Classifier: Intended Audience :: Science/Research
Classifier: Natural Language :: English
Classifier: Programming Language :: Python :: 3
Classifier: Topic :: Scientific/Engineering :: Physics
Requires-Python: >=3.9
Requires-Dist: matplotlib
Requires-Dist: numpy
Requires-Dist: pandas
